LICENSE
MANIFEST.in
README.md
setup.py
Cubie/__init__.py
cubieleds.egg-info/PKG-INFO
cubieleds.egg-info/SOURCES.txt
cubieleds.egg-info/dependency_links.txt
cubieleds.egg-info/top_level.txt
examples/morse.py
examples/ssh_visual.py
src/leds.c
src/leds.h
src/py_leds.c