Metadata-Version: 1.1
Name: cubieleds
Version: 0.1
Summary: A module to control Cubieboard LEDs
Home-page: https://github.com/mikkeloscar/python-cubieleds
Author: Mikkel Oscar Lyderik
Author-email: mikkeloscar@gmail.com
License: GPL
Keywords: Cubie Board leds
Platform: UNKNOWN
Classifier: Development Status :: 4 - Beta
Classifier: Operating System :: POSIX :: Linux
Classifier: License :: OSI Approved :: GNU General Public License (GPL)
Classifier: Intended Audience :: Developers
Classifier: Programming Language :: Python :: 2.7
Classifier: Programming Language :: Python :: 3
Classifier: Topic :: Software Development
Classifier: Topic :: System :: Hardware
